frinx/__init__.py
frinx/client/__init__.py
frinx/client/frinx_conductor_wrapper.py
frinx/client/v1/__init__.py
frinx/client/v1/conductor.py
frinx/client/v1/frinx_conductor_wrapper.py
frinx/client/v2/__init__.py
frinx/client/v2/conductor.py
frinx/client/v2/frinx_conductor_wrapper.py
frinx/common/__init__.py
frinx/common/conductor_enums.py
frinx/common/frinx_rest.py
frinx/common/graphql/__init__.py
frinx/common/graphql/client.py
frinx/common/import_workflows.py
frinx/common/logging/__init__.py
frinx/common/logging/config.py
frinx/common/logging/handlers.py
frinx/common/logging/root_logger.py
frinx/common/logging/settings.py
frinx/common/telemetry/__init__.py
frinx/common/telemetry/common.py
frinx/common/telemetry/enums.py
frinx/common/telemetry/metrics.py
frinx/common/type_aliases.py
frinx/common/util.py
frinx/common/worker/__init__.py
frinx/common/worker/exception.py
frinx/common/worker/service.py
frinx/common/worker/task.py
frinx/common/worker/task_def.py
frinx/common/worker/task_result.py
frinx/common/worker/worker.py
frinx/common/workflow/WORKFLOW_GENERATOR.md
frinx/common/workflow/__init__.py
frinx/common/workflow/service.py
frinx/common/workflow/task.py
frinx/common/workflow/workflow.py
frinx_python_sdk-2.4.1.dist-info/METADATA
frinx_python_sdk-2.4.1.dist-info/WHEEL
frinx_python_sdk-2.4.1.dist-info/RECORD
