Metadata-Version: 2.1
Name: frinx-python-sdk
Version: 2.4.1
Summary: Python SDK for Frinx Machine Workflow Manager
License: Apache 2.0
Keywords: frinx-machine,workflow-manager,conductor
Author: Jozef Volak
Author-email: jozef.volak@elisapolystar.com
Requires-Python: >=3.10,<4.0
Classifier: License :: Other/Proprietary License
Classifier: Programming Language :: Python :: 3
Classifier: Programming Language :: Python :: 3.10
Classifier: Programming Language :: Python :: 3.11
Requires-Dist: aiohttp (>=3.8.4,<4.0.0)
Requires-Dist: prometheus-client (>=0.20.0,<0.21.0)
Requires-Dist: pydantic (>=2.3,<2.6)
Requires-Dist: pydantic-settings (>=2.1.0,<3.0.0)
Requires-Dist: requests (>=2.28.2,<3.0.0)
Requires-Dist: websockets (>=12,<13)
